Workbook
Name ACCES: Assoluti_Iva!$A$193:$C$227
Name CAB: Assoluti_Iva!$A$315:$C$324
Name CDROM: Assoluti_Iva!$A$108:$C$115
Name Codice: #REF!
Name CONT: Assoluti_Iva!$A$326:$C$337
Name CPU: Assoluti_Iva!$A$163:$C$183
Name DANIELE: #REF!
Name DATI: Assoluti_Iva!$A$1:$C$337
Name HD: Assoluti_Iva!$A$79:$C$102
Name IMPO: #REF!
Name IMPORTO: #REF!
Name IO_B: Assoluti_Iva!$A$63:$C$77
Name IVATOT: Assoluti_Iva!$G$1
Name MAIN_B: Assoluti_Iva!$A$20:$C$35
Name MAST: Assoluti_Iva!$A$117:$C$127
Name MEDIA: Assoluti_Iva!$A$151:$C$161
Name MEM: Assoluti_Iva!$A$129:$C$131
Name MO: Assoluti_Iva!$A$6:$C$6
Name MODEM: Assoluti_Iva!$A$133:$C$149
Name MON: Assoluti_Iva!$A$2:$C$15
Name MONLCD: Assoluti_Iva!$A$17:$C$18
Name SOFT: Assoluti_Iva!$A$229:$C$278
Name STAMP: Assoluti_Iva!$A$280:$C$313
Name TAST: Assoluti_Iva!$A$185:$C$191
Name VIDEO_B: Assoluti_Iva!$A$37:$C$61

Sheet Assoluti_Iva
A1: MONITOR | B1: DESC | C1: IMPONIBILE IVA INCLUSA | D1: IVA | E1: MONITOR_DESK
A2: MON.SVGA 0,28 14" AOC 4VLR | B2: 1024 x 768, MPR II, N.I., Energy Star Digital | C2: 281000 | D2: =+C2*0.2 -> 56200 | E2: =_xlfn.CONCAT(A2," ",B2) -> MON.SVGA 0,28 14" AOC 4VLR 1024 x 768, MPR II, N.I., Energy Star Digital
A3: MON.SVGA 0,28 15" AOC 5VLR | B3: 1280 x 1024, MPR II, N.I., Energy Star Digital | C3: 323000 | D3: =+C3*0.2 -> 64600 | E3: =_xlfn.CONCAT(A3," ",B3) -> MON.SVGA 0,28 15" AOC 5VLR 1280 x 1024, MPR II, N.I., Energy Star Digital
A4: MON.SVGA 0,28 15" AOC 5NLR OSD | B4: 1280 x 1024, MPR II, N.I., Energy Star Digital, 69KHz | C4: 344000 | D4: =+C4*0.2 -> 68800 | E4: =_xlfn.CONCAT(A4," ",B4) -> MON.SVGA 0,28 15" AOC 5NLR OSD 1280 x 1024, MPR II, N.I., Energy Star Digital, 69KHz
A5: MON.SVGA 0,28 15" AOC 5GLR+ OSD | B5: 1280 x 1024, MPR II,TCO'92 N.I., Energy Star Digit 69KHz | C5: 361000 | D5: =+C5*0.2 -> 72200 | E5: =_xlfn.CONCAT(A5," ",B5) -> MON.SVGA 0,28 15" AOC 5GLR+ OSD 1280 x 1024, MPR II,TCO'92 N.I., Energy Star Digit 69KHz
A6: MON. 15" 0.23 CM500ET HITACHI | B6: 1152x870, 75 Hz, MPR II,TCO'92, N.I.,Energy Star, P&P | C6: 521000 | D6: =+C6*0.2 -> 104200 | E6: =_xlfn.CONCAT(A6," ",B6) -> MON. 15" 0.23 CM500ET HITACHI 1152x870, 75 Hz, MPR II,TCO'92, N.I.,Energy Star, P&P
A7: MON. 15" 0.28 A500 NEC | B7: 1280x1024, 60Hz, MPR II, Energy Star, P&P | C7: 527000 | D7: =+C7*0.2 -> 105400 | E7: =_xlfn.CONCAT(A7," ",B7) -> MON. 15" 0.28 A500 NEC 1280x1024, 60Hz, MPR II, Energy Star, P&P
A8: MON.SVGA 0,28 17" AOC 7VLR | B8: 1280 x 1024, MPR II, N.I., Energy Star Digital 70KHz | C8: 626000 | D8: =+C8*0.2 -> 125200 | E8: =_xlfn.CONCAT(A8," ",B8) -> MON.SVGA 0,28 17" AOC 7VLR 1280 x 1024, MPR II, N.I., Energy Star Digital 70KHz
A9: MON. 15" 0.25 E500 NEC, Croma Clear | B9: 1280x1024, 65Hz,TCO'95, MPR II, Energy Star, P&P | C9: 656000 | D9: =+C9*0.2 -> 131200 | E9: =_xlfn.CONCAT(A9," ",B9) -> MON. 15" 0.25 E500 NEC, Croma Clear 1280x1024, 65Hz,TCO'95, MPR II, Energy Star, P&P
A10: MON.SVGA 0,26 17" AOC 7GLR OSD | B10: 1280 x 1024,TCO '92, Energy Star Digital, 85KHz | C10: 666000 | D10: =+C10*0.2 -> 133200 | E10: =_xlfn.CONCAT(A10," ",B10) -> MON.SVGA 0,26 17" AOC 7GLR OSD 1280 x 1024,TCO '92, Energy Star Digital, 85KHz
A11: MON. 17" 0.28 A700 NEC | B11: 1280x1024, 65Hz, MPR II, Energy Star, P&P | C11: 882000 | D11: =+C11*0.2 -> 176400 | E11: =_xlfn.CONCAT(A11," ",B11) -> MON. 17" 0.28 A700 NEC 1280x1024, 65Hz, MPR II, Energy Star, P&P
A12: MON. 17" 0.21 CM630ET HITACHI | B12: 1280x1024,80 Hz,TCO '95 N.I.,Energy Star, P&P | C12: 1108000 | D12: =+C12*0.2 -> 221600 | E12: =_xlfn.CONCAT(A12," ",B12) -> MON. 17" 0.21 CM630ET HITACHI 1280x1024,80 Hz,TCO '95 N.I.,Energy Star, P&P
A13: MON. 17" 0.25 P750 NEC, Croma Clear | B13: 1600x1280, 75Hz, TCO'92, MPR II, Energy Star, P&P | C13: 1316000 | D13: =+C13*0.2 -> 263200 | E13: =_xlfn.CONCAT(A13," ",B13) -> MON. 17" 0.25 P750 NEC, Croma Clear 1600x1280, 75Hz, TCO'92, MPR II, Energy Star, P&P
... A15: MON. 21" 0.21 CM802ETM HITACHI | B15: 1600x1280,75 Hz,TCO '95 N.I.,Energy Star, P&P | C15: 2719000 | D15: =+C15*0.2 -> 543800 | E15: =_xlfn.CONCAT(A15," ",B15) -> MON. 21" 0.21 CM802ETM HITACHI 1600x1280,75 Hz,TCO '95 N.I.,Energy Star, P&P
A16: MONITOR LCD | D16: =+C16*0.2 -> 0 | E16: =_xlfn.CONCAT(A16," ",B16) -> MONITOR LCD
A17: MON. 14" LCD 0.28 LCD400V NEC | B17: 1024x768 75Hz, TFT, Energy Star, P&P | C17: 4092000 | D17: =+C17*0.2 -> 818400 | E17: =_xlfn.CONCAT(A17," ",B17) -> MON. 14" LCD 0.28 LCD400V NEC 1024x768 75Hz, TFT, Energy Star, P&P
A18: MON. 20" LCD 0.31 LCD2000sf NEC | B18: 1280X1024 75Hz, TFT, Energy Star, P&P | C18: 13859000 | D18: =+C18*0.2 -> 2771800 | E18: =_xlfn.CONCAT(A18," ",B18) -> MON. 20" LCD 0.31 LCD2000sf NEC 1280X1024 75Hz, TFT, Energy Star, P&P
A19: SCHEDE MADRI | D19: =+C19*0.2 -> 0 | E19: =_xlfn.CONCAT(A19," ",B19) -> SCHEDE MADRI
A20: M/B ASUS SP97-V SVGA SHARE MEMORY | B20: PCI/ISA/Media Bus. SIS 5598 Share Memory, 4XPCI, 3XISA | C20: 167000 | D20: =+C20*0.2 -> 33400 | E20: =_xlfn.CONCAT(A20," ",B20) -> M/B ASUS SP97-V SVGA SHARE MEMORY PCI/ISA/Media Bus. SIS 5598 Share Memory, 4XPCI, 3XISA
A21: M/B ASUS TXP4 | B21: PCI/ISA/Media Bus.TX/ 2 x 168 Pin DIMM, 4 x 72 Pin | C21: 202000 | D21: =+C21*0.2 -> 40400 | E21: =_xlfn.CONCAT(A21," ",B21) -> M/B ASUS TXP4 PCI/ISA/Media Bus.TX/ 2 x 168 Pin DIMM, 4 x 72 Pin
A22: M/B ASUS SP98AGP-X ATX | B22: PCI/ISA/Media Bus. SIS 5591 Share Memory, 3XPCI, 3XISA | C22: 203000 | D22: =+C22*0.2 -> 40600 | E22: =_xlfn.CONCAT(A22," ",B22) -> M/B ASUS SP98AGP-X ATX PCI/ISA/Media Bus. SIS 5591 Share Memory, 3XPCI, 3XISA
A23: M/B ASUS TX-97 - E | B23: PCI/ISA/Media Bus.TX/ 2 x 168 Pin DIMM, 4 x 72 Pin | C23: 234000 | D23: =+C23*0.2 -> 46800 | E23: =_xlfn.CONCAT(A23," ",B23) -> M/B ASUS TX-97 - E PCI/ISA/Media Bus.TX/ 2 x 168 Pin DIMM, 4 x 72 Pin
A24: M/B ASUS TX-97 | B24: PCI/ISA/Media Bus.TX/ 3 x 168 Pin DIMM | C24: 252000 | D24: =+C24*0.2 -> 50400 | E24: =_xlfn.CONCAT(A24," ",B24) -> M/B ASUS TX-97 PCI/ISA/Media Bus.TX/ 3 x 168 Pin DIMM
A25: M/B ASUS TX-97 - XE ATX NO AUDIO | B25: PCI/ISA/Media Bus.TX/ 2 x 168 Pin DIMM, 4 x 72 Pin | C25: 259000 | D25: =+C25*0.2 -> 51800 | E25: =_xlfn.CONCAT(A25," ",B25) -> M/B ASUS TX-97 - XE ATX NO AUDIO PCI/ISA/Media Bus.TX/ 2 x 168 Pin DIMM, 4 x 72 Pin
A26: M/B ASUS P2L97-B | B26: PCI/ISA/Intel 440LX/233-333 Mhz AT BABY | C26: 269000 | D26: =+C26*0.2 -> 53800 | E26: =_xlfn.CONCAT(A26," ",B26) -> M/B ASUS P2L97-B PCI/ISA/Intel 440LX/233-333 Mhz AT BABY
A27: M/B ASUS P55T2P4 430HX 512K P5 | B27: PCI/ISA/Media Bus.Triton II/ZIF7/75-200 MHz | C27: 271000 | D27: =+C27*0.2 -> 54200 | E27: =_xlfn.CONCAT(A27," ",B27) -> M/B ASUS P55T2P4 430HX 512K P5 PCI/ISA/Media Bus.Triton II/ZIF7/75-200 MHz
A28: M/B ASUS P2L97 ATX | B28: PCI/ISA/Intel 440LX/233-333 Mhz | C28: 292000 | D28: =+C28*0.2 -> 58400 | E28: =_xlfn.CONCAT(A28," ",B28) -> M/B ASUS P2L97 ATX PCI/ISA/Intel 440LX/233-333 Mhz
A29: M/B ASUS XP55T2P4 512K ATX P5 | B29: PCI/ISA/Media Bus.Triton II/ZIF7/ 75-200 MHz | C29: 293000 | D29: =+C29*0.2 -> 58600 | E29: =_xlfn.CONCAT(A29," ",B29) -> M/B ASUS XP55T2P4 512K ATX P5 PCI/ISA/Media Bus.Triton II/ZIF7/ 75-200 MHz
A30: M/B ASUS TX-97 -XE ATX -CREATIVE VIBRA16 | B30: PCI/ISA/Media Bus.TX/ 2 x 168 Pin DIMM, 4 x 72 Pin | C30: 307000 | D30: =+C30*0.2 -> 61400 | E30: =_xlfn.CONCAT(A30," ",B30) -> M/B ASUS TX-97 -XE ATX -CREATIVE VIBRA16 PCI/ISA/Media Bus.TX/ 2 x 168 Pin DIMM, 4 x 72 Pin
A31: M/B ASUS P2L97-A ATX+VGA AGP 4MB | B31: PCI/ISA/Intel 440LX/233-333 Mhz ATI 3D Rage Pro AGP | C31: 440000 | D31: =+C31*0.2 -> 88000 | E31: =_xlfn.CONCAT(A31," ",B31) -> M/B ASUS P2L97-A ATX+VGA AGP 4MB PCI/ISA/Intel 440LX/233-333 Mhz ATI 3D Rage Pro AGP
... A35: M/B ASUS P65UP8+PKND DUAL PII | B35: Intel 440FX CPU INTEL RISC i960, SCSI I20 RAID, EXP 1GB | C35: 1579000 | D35: =+C35*0.2 -> 315800 | E35: =_xlfn.CONCAT(A35," ",B35) -> M/B ASUS P65UP8+PKND DUAL PII Intel 440FX CPU INTEL RISC i960, SCSI I20 RAID, EXP 1GB
A36: SCHEDE VIDEO | D36: =+C36*0.2 -> 0 | E36: =_xlfn.CONCAT(A36," ",B36) -> SCHEDE VIDEO
A37: SVGA S3 3D PRO VIRGE 2MB | B37: S3 PRO VIRGE DX 2MB Edo exp. 4MB 3D Acc. | C37: 70000 | D37: =+C37*0.2 -> 14000 | E37: =_xlfn.CONCAT(A37," ",B37) -> SVGA S3 3D PRO VIRGE 2MB S3 PRO VIRGE DX 2MB Edo exp. 4MB 3D Acc.
A38: CREATIVE ECLIPSE 4MB | B38: ACC. 2D/3D 4MB LAGUNA 3D max 1600x1200 | C38: 104000 | D38: =+C38*0.2 -> 20800 | E38: =_xlfn.CONCAT(A38," ",B38) -> CREATIVE ECLIPSE 4MB ACC. 2D/3D 4MB LAGUNA 3D max 1600x1200
A39: ADD-ON MATROX m3D 4MB | B39: MATROX - NEC Power VR PCX2 | C39: 127000 | D39: =+C39*0.2 -> 25400 | E39: =_xlfn.CONCAT(A39," ",B39) -> ADD-ON MATROX m3D 4MB MATROX - NEC Power VR PCX2
A40: ASUS 3DP-V264GT2 4MB TV-OUT | B40: ATI Rage II+ , 2D/3D, DVD Acc.,TV OUT | C40: 162000 | D40: =+C40*0.2 -> 32400 | E40: =_xlfn.CONCAT(A40," ",B40) -> ASUS 3DP-V264GT2 4MB TV-OUT ATI Rage II+ , 2D/3D, DVD Acc.,TV OUT
A41: SVGA MYSTIQUE 220 "BULK" 4MB | B41: MATROX,MGA 1064SG SGRAM | C41: 179000 | D41: =+C41*0.2 -> 35800 | E41: =_xlfn.CONCAT(A41," ",B41) -> SVGA MYSTIQUE 220 "BULK" 4MB MATROX,MGA 1064SG SGRAM
A42: ASUS 3DP-V385GX2 4MB TV-OUT | B42: S3 VIRGE/GX2,2D/3D DVD Acc. VIDEO-IN&TV OUT | C42: 186000 | D42: =+C42*0.2 -> 37200 | E42: =_xlfn.CONCAT(A42," ",B42) -> ASUS 3DP-V385GX2 4MB TV-OUT S3 VIRGE/GX2,2D/3D DVD Acc. VIDEO-IN&TV OUT
A43: ASUS V385GX2 AGP 4MB TV-OUT | B43: S3 VIRGE/GX2,2D/3D DVD Acc. VIDEO-IN&TV OUT | C43: 186000 | D43: =+C43*0.2 -> 37200 | E43: =_xlfn.CONCAT(A43," ",B43) -> ASUS V385GX2 AGP 4MB TV-OUT S3 VIRGE/GX2,2D/3D DVD Acc. VIDEO-IN&TV OUT
A44: CREATIVE GRAPHIC EXXTREME 4MB | B44: ACC. 2D/3D 4MB SGRAM T.I.9735AC | C44: 203000 | D44: =+C44*0.2 -> 40600 | E44: =_xlfn.CONCAT(A44," ",B44) -> CREATIVE GRAPHIC EXXTREME 4MB ACC. 2D/3D 4MB SGRAM T.I.9735AC
A45: SVGA MYSTIQUE 220 4MB | B45: MATROX,MGA 1064SG SGRAM | C45: 212000 | D45: =+C45*0.2 -> 42400 | E45: =_xlfn.CONCAT(A45," ",B45) -> SVGA MYSTIQUE 220 4MB MATROX,MGA 1064SG SGRAM
A46: SVGA ACC. 3D/FX VOODO RUSH 4MB | B46: ACC.2D/3D 3D/FX Voodo Rush+AT25 Game+Giochi | C46: 222000 | D46: =+C46*0.2 -> 44400 | E46: =_xlfn.CONCAT(A46," ",B46) -> SVGA ACC. 3D/FX VOODO RUSH 4MB ACC.2D/3D 3D/FX Voodo Rush+AT25 Game+Giochi
A47: SVGA ACC. 3D/FX VOODO RUSH 6MB | B47: ACC.2D/3D 3D/FX Voodoo Rush+AT25 Game+Giochi | C47: 245000 | D47: =+C47*0.2 -> 49000 | E47: =_xlfn.CONCAT(A47," ",B47) -> SVGA ACC. 3D/FX VOODO RUSH 6MB ACC.2D/3D 3D/FX Voodoo Rush+AT25 Game+Giochi
A48: RAINBOW R. TV | B48: MATROX | C48: 251000 | D48: =+C48*0.2 -> 50200 | E48: =_xlfn.CONCAT(A48," ",B48) -> RAINBOW R. TV MATROX
... A61: ASUS 3DP- V500TX 16MB Work.Prof.3d | B61: 3D LABS GLINT500TX,8MB VRAM Frame Buffer,8MB DRAM | C61: 1487000 | D61: =+C61*0.2 -> 297400 | E61: =_xlfn.CONCAT(A61," ",B61) -> ASUS 3DP- V500TX 16MB Work.Prof.3d 3D LABS GLINT500TX,8MB VRAM Frame Buffer,8MB DRAM
A62: SCHEDE I/O | D62: =+C62*0.2 -> 0 | E62: =_xlfn.CONCAT(A62," ",B62) -> SCHEDE I/O
A63: Contr. PCI SCSI | B63: Fast SCSI-2 | C63: 101000 | D63: =+C63*0.2 -> 20200 | E63: =_xlfn.CONCAT(A63," ",B63) -> Contr. PCI SCSI Fast SCSI-2
A64: Contr. PCI EIDE | B64: Tekram 690B, 4 canali EIDE | C64: 38000 | D64: =+C64*0.2 -> 7600 | E64: =_xlfn.CONCAT(A64," ",B64) -> Contr. PCI EIDE Tekram 690B, 4 canali EIDE
A65: Contr. PCI SC200 SCSI-2 | B65: ASUS NCR-53C810 Ultra Fast, SCSI-2 | C65: 137000 | D65: =+C65*0.2 -> 27400 | E65: =_xlfn.CONCAT(A65," ",B65) -> Contr. PCI SC200 SCSI-2 ASUS NCR-53C810 Ultra Fast, SCSI-2
A66: Contr. PCI SC875 Wide SCSI, SCSI-2 | B66: ASUS NCR-53C875 Ultra Fast, Wide SCSI e SCSI-2 | C66: 222000 | D66: =+C66*0.2 -> 44400 | E66: =_xlfn.CONCAT(A66," ",B66) -> Contr. PCI SC875 Wide SCSI, SCSI-2 ASUS NCR-53C875 Ultra Fast, Wide SCSI e SCSI-2
A67: Contr. PCI AHA 2940AU SCSI-2 | B67: Adaptec 2940 Ultra Fast, SCSI-2, sw EZ SCSI 4.0 | C67: 501000 | D67: =+C67*0.2 -> 100200 | E67: =_xlfn.CONCAT(A67," ",B67) -> Contr. PCI AHA 2940AU SCSI-2 Adaptec 2940 Ultra Fast, SCSI-2, sw EZ SCSI 4.0
A68: Contr. PCI AHA 2940UW Wide SCSI OEM | B68: Adaptec 2940 Ultra Fast, Wide SCSI e SCSI-2 | C68: 428000 | D68: =+C68*0.2 -> 85600 | E68: =_xlfn.CONCAT(A68," ",B68) -> Contr. PCI AHA 2940UW Wide SCSI OEM Adaptec 2940 Ultra Fast, Wide SCSI e SCSI-2
A69: Contr. PCI AHA 2940UW Wide SCSI | B69: Adaptec 2940 Ultra Fast, Wide SCSI e SCSI-2, sw EZ SCSI | C69: 561000 | D69: =+C69*0.2 -> 112200 | E69: =_xlfn.CONCAT(A69," ",B69) -> Contr. PCI AHA 2940UW Wide SCSI Adaptec 2940 Ultra Fast, Wide SCSI e SCSI-2, sw EZ SCSI
A70: Contr.PCI DA2100 Dual Wide SCSI | B70: ASUS Infotrend-500127 dual Ultra Fast, Wide SCSI, RAID | C70: 1578000 | D70: =+C70*0.2 -> 315600 | E70: =_xlfn.CONCAT(A70," ",B70) -> Contr.PCI DA2100 Dual Wide SCSI ASUS Infotrend-500127 dual Ultra Fast, Wide SCSI, RAID
A71: Scheda 2 porte seriali, 1 porta parallela | B71: 16550 Fast UART | C71: 34000 | D71: =+C71*0.2 -> 6800 | E71: =_xlfn.CONCAT(A71," ",B71) -> Scheda 2 porte seriali, 1 porta parallela 16550 Fast UART
A72: Scheda singola seriale | C72: 20000 | D72: =+C72*0.2 -> 4000 | E72: =_xlfn.CONCAT(A72," ",B72) -> Scheda singola seriale
A73: Scheda doppia seriale | C73: 23000 | D73: =+C73*0.2 -> 4600 | E73: =_xlfn.CONCAT(A73," ",B73) -> Scheda doppia seriale
A74: Scheda 4 porte seriali | C74: 98000 | D74: =+C74*0.2 -> 19600 | E74: =_xlfn.CONCAT(A74," ",B74) -> Scheda 4 porte seriali
A75: Scheda 8 porte seriali | C75: 251000 | D75: =+C75*0.2 -> 50200 | E75: =_xlfn.CONCAT(A75," ",B75) -> Scheda 8 porte seriali
A76: Scheda singola parallela | C76: 15000 | D76: =+C76*0.2 -> 3000 | E76: =_xlfn.CONCAT(A76," ",B76) -> Scheda singola parallela
A77: Scheda 2 porte joystick | C77: 14000 | D77: =+C77*0.2 -> 2800 | E77: =_xlfn.CONCAT(A77," ",B77) -> Scheda 2 porte joystick
A78: HARD DISK | D78: =+C78*0.2 -> 0 | E78: =_xlfn.CONCAT(A78," ",B78) -> HARD DISK
A79: HARD DISK 2.5" 2,1GB U.Dma | B79: 2,5" 12mm HITACHI - DK226A-21 | C79: 399000 | D79: =+C79*0.2 -> 79800 | E79: =_xlfn.CONCAT(A79," ",B79) -> HARD DISK 2.5" 2,1GB U.Dma 2,5" 12mm HITACHI - DK226A-21
A80: HD 2,1 GB Ultra DMA 5400rpm | B80: 3,5" ULTRA DMA FUJITSU | C80: 259000 | D80: =+C80*0.2 -> 51800 | E80: =_xlfn.CONCAT(A80," ",B80) -> HD 2,1 GB Ultra DMA 5400rpm 3,5" ULTRA DMA FUJITSU
A81: HD 3,2 GB Ultra DMA 5400rpm | B81: 3,5" ULTRA DMA FUJITSU | C81: 324000 | D81: =+C81*0.2 -> 64800 | E81: =_xlfn.CONCAT(A81," ",B81) -> HD 3,2 GB Ultra DMA 5400rpm 3,5" ULTRA DMA FUJITSU
A82: HD 4,3 GB Ultra DMA 5400rpm | B82: 3,5" ULTRA DMA FUJITSU | C82: 378000 | D82: =+C82*0.2 -> 75600 | E82: =_xlfn.CONCAT(A82," ",B82) -> HD 4,3 GB Ultra DMA 5400rpm 3,5" ULTRA DMA FUJITSU
A83: HD 5,2 GB Ultra DMA 5400rpm | B83: 3,5" ULTRA DMA FUJITSU | C83: 469000 | D83: =+C83*0.2 -> 93800 | E83: =_xlfn.CONCAT(A83," ",B83) -> HD 5,2 GB Ultra DMA 5400rpm 3,5" ULTRA DMA FUJITSU
A84: HD 6,4 GB Ultra DMA 5400rpm | B84: 3,5" ULTRA DMA FUJITSU | C84: 556000 | D84: =+C84*0.2 -> 111200 | E84: =_xlfn.CONCAT(A84," ",B84) -> HD 6,4 GB Ultra DMA 5400rpm 3,5" ULTRA DMA FUJITSU
A85: HD 2 GB SCSI III 5400 rpm | B85: 3,5" SCSI QUANTUM FIREBALL ST | C85: 476000 | D85: =+C85*0.2 -> 95200 | E85: =_xlfn.CONCAT(A85," ",B85) -> HD 2 GB SCSI III 5400 rpm 3,5" SCSI QUANTUM FIREBALL ST
A86: HD 3,2 GB SCSI III 5400rpm | B86: 3,5" SCSI QUANTUM FIREBALL ST | C86: 477000 | D86: =+C86*0.2 -> 95400 | E86: =_xlfn.CONCAT(A86," ",B86) -> HD 3,2 GB SCSI III 5400rpm 3,5" SCSI QUANTUM FIREBALL ST
A87: HD 4,3 GB SCSI 5400 rpm | B87: 3,5" SCSI QUANTUM FIREBALL ST | C87: 556000 | D87: =+C87*0.2 -> 111200 | E87: =_xlfn.CONCAT(A87," ",B87) -> HD 4,3 GB SCSI 5400 rpm 3,5" SCSI QUANTUM FIREBALL ST
A88: HD 4,5 GB SCSI ULTRA WIDE 7200rpm | B88: 3,5" SCSI III, QUANTUM VIKING | C88: 695000 | D88: =+C88*0.2 -> 139000 | E88: =_xlfn.CONCAT(A88," ",B88) -> HD 4,5 GB SCSI ULTRA WIDE 7200rpm 3,5" SCSI III, QUANTUM VIKING
A89: HD 4,5 GB SCSI ULTRA WIDE 10.000rpm | B89: 3,5" SCSI U.W. SEAGATE CHEETAH | C89: 1279000 | D89: =+C89*0.2 -> 255800 | E89: =_xlfn.CONCAT(A89," ",B89) -> HD 4,5 GB SCSI ULTRA WIDE 10.000rpm 3,5" SCSI U.W. SEAGATE CHEETAH
A90: FDD 1,44MB | B90: PANASONIC | C90: 35000 | D90: =+C90*0.2 -> 7000 | E90: =_xlfn.CONCAT(A90," ",B90) -> FDD 1,44MB PANASONIC
... A96: JAZ DRIVE 1GB EXT. | B96: IOMEGA | C96: 743000 | D96: =+C96*0.2 -> 148600 | E96: =_xlfn.CONCAT(A96," ",B96) -> JAZ DRIVE 1GB EXT. IOMEGA
A97: KIT 10 CARTUCCE ZIP DRIVE | C97: 271000 | D97: =+C97*0.2 -> 54200 | E97: =_xlfn.CONCAT(A97," ",B97) -> KIT 10 CARTUCCE ZIP DRIVE
A98: KIT 3 CARTUCCE JAZ DRIVE | C98: 632000 | D98: =+C98*0.2 -> 126400 | E98: =_xlfn.CONCAT(A98," ",B98) -> KIT 3 CARTUCCE JAZ DRIVE
A99: KIT 3 CARTUCCE 120MB 3M | B99: per LS-120 | C99: 90000 | D99: =+C99*0.2 -> 18000 | E99: =_xlfn.CONCAT(A99," ",B99) -> KIT 3 CARTUCCE 120MB 3M per LS-120
A100: FRAME HDD | B100: Kit montaggio Hard Disk 3,5" | C100: 4000 | D100: =+C100*0.2 -> 800 | E100: =_xlfn.CONCAT(A100," ",B100) -> FRAME HDD Kit montaggio Hard Disk 3,5"
A101: FRAME FDD | B101: Kit montaggio Floppy Disk Drive 3,5" | C101: 5000 | D101: =+C101*0.2 -> 1000 | E101: =_xlfn.CONCAT(A101," ",B101) -> FRAME FDD Kit montaggio Floppy Disk Drive 3,5"
A102: FRAME REMOVIBILE 3.5" | B102: Kit FRAME REMOVIBILE per HDD 3,5" | C102: 41000 | D102: =+C102*0.2 -> 8200 | E102: =_xlfn.CONCAT(A102," ",B102) -> FRAME REMOVIBILE 3.5" Kit FRAME REMOVIBILE per HDD 3,5"
A103: MAGNETO-OTTICI | D103: =+C103*0.2 -> 0 | E103: =_xlfn.CONCAT(A103," ",B103) -> MAGNETO-OTTICI
A104: M.O. + CD 4X, PD 2000 INT. 650 MB | B104: PLASMON PD2000I | C104: 737000 | D104: =+C104*0.2 -> 147400 | E104: =_xlfn.CONCAT(A104," ",B104) -> M.O. + CD 4X, PD 2000 INT. 650 MB PLASMON PD2000I
A105: M.O. + CD 4X, PD 2000 EXT. 650 MB | B105: PLASMON PD2000E | C105: 910000 | D105: =+C105*0.2 -> 182000 | E105: =_xlfn.CONCAT(A105," ",B105) -> M.O. + CD 4X, PD 2000 EXT. 650 MB PLASMON PD2000E
A106: KIT 5 CARTUCCE 650 MB | C106: 241000 | D106: =+C106*0.2 -> 48200 | E106: =_xlfn.CONCAT(A106," ",B106) -> KIT 5 CARTUCCE 650 MB
A107: CD ROM | D107: =+C107*0.2 -> 0 | E107: =_xlfn.CONCAT(A107," ",B107) -> CD ROM
A108: CD ROM 24X HITACHI CDR 8330 | B108: 24 velocita',EIDE | C108: 112000 | D108: =+C108*0.2 -> 22400 | E108: =_xlfn.CONCAT(A108," ",B108) -> CD ROM 24X HITACHI CDR 8330 24 velocita',EIDE
A109: CD ROM 24X CREATIVE | B109: 24 velocita',EIDE | C109: 113000 | D109: =+C109*0.2 -> 22600 | E109: =_xlfn.CONCAT(A109," ",B109) -> CD ROM 24X CREATIVE 24 velocita',EIDE
A110: CD ROM 24X PIONEER 502-S Bulk | B110: 24 velocita',EIDE,SLOT-IN | C110: 121000 | D110: =+C110*0.2 -> 24200 | E110: =_xlfn.CONCAT(A110," ",B110) -> CD ROM 24X PIONEER 502-S Bulk 24 velocita',EIDE,SLOT-IN
A111: CD ROM 34X ASUS | B111: 34 velocita',EIDE | C111: 160000 | D111: =+C111*0.2 -> 32000 | E111: =_xlfn.CONCAT(A111," ",B111) -> CD ROM 34X ASUS 34 velocita',EIDE
A112: CD ROM 24X SCSI NEC | B112: 24 velocita',SCSI | C112: 195000 | D112: =+C112*0.2 -> 39000 | E112: =_xlfn.CONCAT(A112," ",B112) -> CD ROM 24X SCSI NEC 24 velocita',SCSI
A113: CD ROM 32X SCSI WAITEC | B113: 32 velocita',SCSI | C113: 215000 | D113: =+C113*0.2 -> 43000 | E113: =_xlfn.CONCAT(A113," ",B113) -> CD ROM 32X SCSI WAITEC 32 velocita',SCSI
A114: CD ROM PLEXTOR PX-32TSI | B114: 32 velocita',SCSI | C114: 321000 | D114: =+C114*0.2 -> 64200 | E114: =_xlfn.CONCAT(A114," ",B114) -> CD ROM PLEXTOR PX-32TSI 32 velocita',SCSI
A115: DVD CREATIVE KIT ENCORE DXR2 | B115: CREATIVE | C115: 614000 | D115: =+C115*0.2 -> 122800 | E115: =_xlfn.CONCAT(A115," ",B115) -> DVD CREATIVE KIT ENCORE DXR2 CREATIVE
A116: MASTERIZZATORI | D116: =+C116*0.2 -> 0 | E116: =_xlfn.CONCAT(A116," ",B116) -> MASTERIZZATORI
A117: CONFEZIONE 10 CDR 74' | B117: Kit 10 pz. | C117: 30000 | D117: =+C117*0.2 -> 6000 | E117: =_xlfn.CONCAT(A117," ",B117) -> CONFEZIONE 10 CDR 74' Kit 10 pz.
A118: CD RISCRIVIBILE 74' | B118: VERBATIM | C118: 34000 | D118: =+C118*0.2 -> 6800 | E118: =_xlfn.CONCAT(A118," ",B118) -> CD RISCRIVIBILE 74' VERBATIM
A119: CONFEZIONE 10 CDR 74' KODAK | B119: Kit 10 pz. | C119: 35000 | D119: =+C119*0.2 -> 7000 | E119: =_xlfn.CONCAT(A119," ",B119) -> CONFEZIONE 10 CDR 74' KODAK Kit 10 pz.
A120: SOFTWARE LABELLER CD KIT | B120: Software per creazione etichette CD | C120: 77000 | D120: =+C120*0.2 -> 15400 | E120: =_xlfn.CONCAT(A120," ",B120) -> SOFTWARE LABELLER CD KIT Software per creazione etichette CD
A121: WAITEC WT48/1 - GEAR - | B121: int. 4 WRITE 8 READ | C121: 723000 | D121: =+C121*0.2 -> 144600 | E121: =_xlfn.CONCAT(A121," ",B121) -> WAITEC WT48/1 - GEAR - int. 4 WRITE 8 READ
...

Sheet Giudizio
A1: Nome | B1: Punteggio | C1: Esito | D1: Esito_Cercavert
A2: Tamburini Ivo | B2: 40 | C2: =+IF(Table_1[[#This Row],[Column2]]<40,"respinto",IF(Table_1[[#This Row],[Column2]]<60,"sufficiente",IF(Table_1[[#This Row],[Column2]]<70,"discreto","buono"))) -> sufficiente | D2: =+VLOOKUP(Table_1[[#This Row],[Column2]],Legenda_Giudizi!$B$2:$C$6,2,TRUE) -> sufficiente
A3: Tamburini Lorenzo | B3: 60 | C3: =+IF(Table_1[[#This Row],[Column2]]<40,"respinto",IF(Table_1[[#This Row],[Column2]]<60,"sufficiente",IF(Table_1[[#This Row],[Column2]]<70,"discreto","buono"))) -> discreto | D3: =+VLOOKUP(Table_1[[#This Row],[Column2]],Legenda_Giudizi!$B$2:$C$6,2,TRUE) -> discreto
A4: Zadra Loris | B4: 60 | C4: =+IF(Table_1[[#This Row],[Column2]]<40,"respinto",IF(Table_1[[#This Row],[Column2]]<60,"sufficiente",IF(Table_1[[#This Row],[Column2]]<70,"discreto","buono"))) -> discreto | D4: =+VLOOKUP(Table_1[[#This Row],[Column2]],Legenda_Giudizi!$B$2:$C$6,2,TRUE) -> discreto
A5: Gagliardi Daniele | B5: 40 | C5: =+IF(Table_1[[#This Row],[Column2]]<40,"respinto",IF(Table_1[[#This Row],[Column2]]<60,"sufficiente",IF(Table_1[[#This Row],[Column2]]<70,"discreto","buono"))) -> sufficiente | D5: =+VLOOKUP(Table_1[[#This Row],[Column2]],Legenda_Giudizi!$B$2:$C$6,2,TRUE) -> sufficiente
A6: Maria Genta | B6: 70 | C6: =+IF(Table_1[[#This Row],[Column2]]<40,"respinto",IF(Table_1[[#This Row],[Column2]]<60,"sufficiente",IF(Table_1[[#This Row],[Column2]]<70,"discreto","buono"))) -> buono | D6: =+VLOOKUP(Table_1[[#This Row],[Column2]],Legenda_Giudizi!$B$2:$C$6,2,TRUE) -> buono
A7: Fabrizio Corona | B7: 0 | C7: =+IF(Table_1[[#This Row],[Column2]]<40,"respinto",IF(Table_1[[#This Row],[Column2]]<60,"sufficiente",IF(Table_1[[#This Row],[Column2]]<70,"discreto","buono"))) -> respinto | D7: =+VLOOKUP(Table_1[[#This Row],[Column2]],Legenda_Giudizi!$B$2:$C$6,2,TRUE) -> respinto
A8: Roberto Scarola | B8: 0 | C8: =+IF(Table_1[[#This Row],[Column2]]<40,"respinto",IF(Table_1[[#This Row],[Column2]]<60,"sufficiente",IF(Table_1[[#This Row],[Column2]]<70,"discreto","buono"))) -> respinto | D8: =+VLOOKUP(Table_1[[#This Row],[Column2]],Legenda_Giudizi!$B$2:$C$6,2,TRUE) -> respinto

Sheet Legenda_Giudizi
B2: Punteggio | C2: Esito
B3: 0 | C3: respinto
B4: 40 | C4: sufficiente
B5: 60 | C5: discreto
B6: 70 | C6: buono

Sheet Fatture
A1: Data | B1: Cliente | C1: Categoria | D1: Importo fattura | E1: Spese di spedizione | G1: Cliente | H1: Conteggio_Fatture
A2: 36529 | B2: Ferguson and Bardell | C2: Abbigliamento | D2: 50000 | E2: 16 | G2: H&B | H2: =+COUNTIF($B$1:$B$80,G2) -> 2
A3: 36534 | B3: Chateau St. Mark | C3: Abbigliamento | D3: 29970 | E3: 29 | G3: Allstate | H3: =+COUNTIF($B$1:$B$80,G3) -> 1
A4: 36537 | B4: H&B | C4: Svago | D4: 27560 | E4: 21 | G4: Canon USA | H4: =+COUNTIF($B$1:$B$80,G4) -> 1
A5: 36543 | B5: Fletcher's for Children | C5: Attrezzatura | D5: 43500 | E5: 29 | G5: America Online | H5: =+COUNTIF($B$1:$B$80,G5) -> 1
A6: 36545 | B6: Barber Shop | C6: Personale | D6: 13500 | E6: 15 | G6: Biobottoms | H6: =+COUNTIF($B$1:$B$80,G6) -> 4
A7: 36547 | B7: Allstate | C7: Assicurazione | D7: 50800 | E7: 22 | G7: Epcot Center | H7: =+COUNTIF($B$1:$B$80,G7) -> 2
A8: 36548 | B8: Canon USA | C8: Ufficio | D8: 98450 | E8: 21 | G8: Biergarten | H8: =+COUNTIF($B$1:$B$80,G8) -> 1
A9: 36551 | B9: H&B | C9: Svago | D9: 45890 | E9: 18
A10: 36552 | B10: America Online | C10: Posta elettronica | D10: 7950 | E10: 23
A11: 36553 | B11: Deluxe Business Forms | C11: Ufficio | D11: 87450 | E11: 24
A12: 36554 | B12: Agora Publishing | C12: Manuali | D12: 295000 | E12: 27 | G12: Categorie | H12: Totale_Fatturato
A13: 36555 | B13: Fletcher's for Children | C13: Mobili | D13: 348980 | E13: 15 | G13: Abbigliamento | H13: =+SUMIF($C$1:$C$80,G13,$D$1:$D$80) -> 611780
A14: 36558 | B14: Furrow Building Materials | C14: Educazione dei figli | D14: 127490 | E14: 17 | G14: Alimentari | H14: =+SUMIF($C$1:$C$80,G14,$D$1:$D$80) -> 30860
A15: 36558 | B15: Chinaberry Book | C15: Svago | D15: 49400 | E15: 13 | G15: Personale | H15: =+SUMIF($C$1:$C$80,G15,$D$1:$D$80) -> 54000
A16: 36573 | B16: Alaska Airlines | C16: Viaggio d'affari | D16: 201000 | E16: 14 | G16: Hardware | H16: =+SUMIF($C$1:$C$80,G16,$D$1:$D$80) -> 6765600
A17: 36573 | B17: American Airlines | C17: Viaggio d'affari | D17: 1368000 | E17: 28
A18: 36576 | B18: DeFrisco's | C18: Ristorante | D18: 36850 | E18: 16
A19: 36580 | B19: Biobottoms | C19: Abbigliamento | D19: 151500 | E19: 13
A20: 36589 | B20: Barber Shop | C20: Personale | D20: 13500 | E20: 20 | G20: Cliente | H20: Totale_Fatturato
A21: 36593 | B21: Airport City Taxi | C21: Viaggio d'affari: trasporto | D21: 17000 | E21: 18 | G21: H&B | H21: =+SUMIF($B$1:$B$80,G21,$D$1:$D$80) -> 73450
A22: 36594 | B22: Epcot Center | C22: Svago | D22: 35900 | E22: 16 | G22: Allstate | H22: =+SUMIF($B$1:$B$80,G22,$D$1:$D$80) -> 50800
A23: 36594 | B23: Biergarten | C23: Viaggio d'affari: pasti | D23: 27270 | E23: 14 | G23: Canon USA | H23: =+SUMIF($B$1:$B$80,G23,$D$1:$D$80) -> 98450
A24: 36594 | B24: Dolphin Hotel | C24: Viaggio d'affari: pasti | D24: 13400 | E24: 14 | G24: America Online | H24: =+SUMIF($B$1:$B$80,G24,$D$1:$D$80) -> 7950
A25: 36595 | B25: Biobottoms | C25: Abbigliamento | D25: 19000 | E25: 17 | G25: Biobottoms | H25: =+SUMIF($B$1:$B$80,G25,$D$1:$D$80) -> 283000
A26: 36595 | B26: Epcot Center | C26: Svago | D26: 71800 | E26: 18 | G26: Epcot Center | H26: =+SUMIF($B$1:$B$80,G26,$D$1:$D$80) -> 107700
A27: 36595 | B27: Dolphin Hotel | C27: Viaggio d'affari: pasti | D27: 12280 | E27: 14 | G27: Biergarten | H27: =+SUMIF($B$1:$B$80,G27,$D$1:$D$80) -> 27270
A28: 36595 | B28: Dolphin Hotel | C28: Viaggio d'affari: pasti | D28: 14670 | E28: 17
A29: 36596 | B29: After the Stork | C29: Abbigliamento | D29: 163500 | E29: 18
A30: 36596 | B30: DAK Industries | C30: Mobili | D30: 183900 | E30: 26
A31: 36596 | B31: Chambers | C31: Regali | D31: 43500 | E31: 16
A32: 36596 | B32: Cap n Jacks | C32: Viaggio d'affari: pasti | D32: 10730 | E32: 17
A33: 36596 | B33: Dallas Airport | C33: Viaggio d'affari: pasti | D33: 11210 | E33: 25
A34: 36596 | B34: Avis | C34: Viaggio d'affari: trasporto | D34: 127950 | E34: 20
A35: 36597 | B35: Annual fee | C35: Operazioni bancarie | D35: 20000 | E35: 23
A36: 36597 | B36: Concession Air, Portland Airport | C36: Viaggio d'affari: pasti | D36: 7850 | E36: 25
A37: 36598 | B37: Furrow Building Materials | C37: Educazione dei figli | D37: 127490 | E37: 21
A38: 36598 | B38: Bagels | C38: Ristorante | D38: 3950 | E38: 17
A39: 36598 | B39: Ferguson and Bardell | C39: Salute | D39: 50000 | E39: 15
... A80: 36705 | B80: Flower Market | C80: Alimentari | D80: 4950 | E80: 28
